OpenrestyZuijiaShijian/README.md
OpenrestyZuijiaShijian/__init__.py
OpenrestyZuijiaShijian/__main__.py
OpenrestyZuijiaShijian/file.epub
OpenrestyZuijiaShijian/index.html
OpenrestyZuijiaShijian/css/__init__.py
OpenrestyZuijiaShijian/css/annotations.css
OpenrestyZuijiaShijian/css/main.css
OpenrestyZuijiaShijian/css/normalize.css
OpenrestyZuijiaShijian/css/popup.css
OpenrestyZuijiaShijian/font/__init__.py
OpenrestyZuijiaShijian/font/fontello.eot
OpenrestyZuijiaShijian/font/fontello.svg
OpenrestyZuijiaShijian/font/fontello.ttf
OpenrestyZuijiaShijian/font/fontello.woff
OpenrestyZuijiaShijian/img/__init__.py
OpenrestyZuijiaShijian/img/annotator-glyph-sprite.png
OpenrestyZuijiaShijian/img/annotator-icon-sprite.png
OpenrestyZuijiaShijian/img/apple-touch-icon.png
OpenrestyZuijiaShijian/img/cancelfullscreen.png
OpenrestyZuijiaShijian/img/close.png
OpenrestyZuijiaShijian/img/fullscreen.png
OpenrestyZuijiaShijian/img/loader.gif
OpenrestyZuijiaShijian/img/menu-icon.png
OpenrestyZuijiaShijian/img/save.png
OpenrestyZuijiaShijian/img/saved.png
OpenrestyZuijiaShijian/img/settings-s.png
OpenrestyZuijiaShijian/img/settings.png
OpenrestyZuijiaShijian/img/star.png
OpenrestyZuijiaShijian/js/__init__.py
OpenrestyZuijiaShijian/js/epub.js
OpenrestyZuijiaShijian/js/epub.min.js
OpenrestyZuijiaShijian/js/epub.min.map
OpenrestyZuijiaShijian/js/hooks.min.js
OpenrestyZuijiaShijian/js/hooks.min.map
OpenrestyZuijiaShijian/js/reader.js
OpenrestyZuijiaShijian/js/reader.js.map
OpenrestyZuijiaShijian/js/reader.min.js
OpenrestyZuijiaShijian/js/reader.min.map
OpenrestyZuijiaShijian/js/hooks/__init__.py
OpenrestyZuijiaShijian/js/hooks/extensions/__init__.py
OpenrestyZuijiaShijian/js/hooks/extensions/highlight.js
OpenrestyZuijiaShijian/js/libs/__init__.py
OpenrestyZuijiaShijian/js/libs/jquery.min.js
OpenrestyZuijiaShijian/js/libs/localforage.min.js
OpenrestyZuijiaShijian/js/libs/screenfull.js
OpenrestyZuijiaShijian/js/libs/screenfull.min.js
OpenrestyZuijiaShijian/js/libs/zip.min.js
openresty_zuijia_shijian-2024.3.1.0.dist-info/METADATA
openresty_zuijia_shijian-2024.3.1.0.dist-info/WHEEL
openresty_zuijia_shijian-2024.3.1.0.dist-info/entry_points.txt
openresty_zuijia_shijian-2024.3.1.0.dist-info/top_level.txt
openresty_zuijia_shijian-2024.3.1.0.dist-info/RECORD
